Modelo.py
VisaoHTML.py
setup.py
modelo_visao.egg-info/PKG-INFO
modelo_visao.egg-info/SOURCES.txt
modelo_visao.egg-info/dependency_links.txt
modelo_visao.egg-info/requires.txt
modelo_visao.egg-info/top_level.txt