Metadata-Version: 1.1
Name: modelo-visao
Version: 1.1
Summary: Projeto traz bibliotecas do Modelo e VisaoHTML para o appLojas
Home-page: https://github.com/plimo263
Author: Marcos Felipe da Silva Jardim
Author-email: plimo263@gmail.com
License: MIT
Platform: UNKNOWN
Classifier: Programming Language :: Python :: 3
Classifier: Programming Language :: Python :: 3.2
Classifier: Programming Language :: Python :: 3.3
Classifier: Programming Language :: Python :: 3.4
Classifier: Programming Language :: Python :: 3.5
Classifier: Programming Language :: Python :: 3.6
